{
	"name": "CopyPipeline_MoviesData",
	"properties": {
		"description": "This pipeline is created to move data from input folder to output folder in Azure Blob Storage.",
		"activities": [
			{
				"name": "Copy_9m8",
				"type": "Copy",
				"dependsOn": [],
				"policy": {
					"timeout": "0.12:00:00",
					"retry": 0,
					"retryIntervalInSeconds": 30,
					"secureOutput": false,
					"secureInput": false
				},
				"userProperties": [
					{
						"name": "Source",
						"value": "input//moviesDB2.csv"
					},
					{
						"name": "Destination",
						"value": "output//output_06_26_2024.txt"
					}
				],
				"typeProperties": {
					"source": {
						"type": "BinarySource",
						"storeSettings": {
							"type": "AzureBlobStorageReadSettings",
							"recursive": true
						},
						"formatSettings": {
							"type": "BinaryReadSettings"
						}
					},
					"sink": {
						"type": "BinarySink",
						"storeSettings": {
							"type": "AzureBlobStorageWriteSettings"
						}
					},
					"enableStaging": false,
					"validateDataConsistency": false
				},
				"inputs": [
					{
						"referenceName": "SourceDataset_9m8",
						"type": "DatasetReference"
					}
				],
				"outputs": [
					{
						"referenceName": "DestinationDataset_9m8",
						"type": "DatasetReference"
					}
				]
			}
		],
		"annotations": []
	}
}